atacnet/__init__.py
atacnet/atacnet.py
atacnet/draw.py
atacnet/inverse_covariance.py
atacnet/metacells.py
atacnet/metrics.py
atacnet/pyquic/QUIC.C
atacnet/pyquic/QUIC.h
atacnet/pyquic/pyquic.cpp
atacnet/pyquic/pyquic.pyx
atacnet/quic_graph_lasso.py
atacnet/rank_correlation.py
atacnet/adaptative_graph_lasso.py
atacnet/pyquic.cpython-310-x86_64-linux-gnu.so
atacnet-0.1.8.dist-info/LICENSE.txt
atacnet-0.1.8.dist-info/METADATA
atacnet-0.1.8.dist-info/WHEEL
atacnet-0.1.8.dist-info/RECORD
