Metadata-Version: 2.1
Name: atacnet
Version: 0.1.8
Summary: Package for building co-accessibility networks from ATAC-seq data.
License: GPL-3.0-only
Author: Rémi Trimbour
Author-email: remi.trimbour@pasteur.fr
Requires-Python: >=3.7,<3.13
Classifier: License :: OSI Approved :: GNU General Public License v3 (GPLv3)
Classifier: Programming Language :: Python :: 3
Classifier: Programming Language :: Python :: 3.7
Classifier: Programming Language :: Python :: 3.8
Classifier: Programming Language :: Python :: 3.9
Classifier: Programming Language :: Python :: 3.10
Classifier: Programming Language :: Python :: 3.11
Requires-Dist: joblib (>=1.1.0,<2.0.0)
Requires-Dist: numpy (>=1.25.0,<2.0.0)
Requires-Dist: pandas (>=2.1.1,<3.0.0)
Requires-Dist: rich (>=10.12.0,<11.0.0)
Requires-Dist: scanpy (>=1.8.1,<2.0.0)
Requires-Dist: scikit-learn (>=1.3.1,<2.0.0)
